pytest_assert_error.py
tests/__init__.py
tests/conftest.py
tests/test_change_assert.py
pytest_change_assert-1.3.dist-info/AUTHORS
pytest_change_assert-1.3.dist-info/METADATA
pytest_change_assert-1.3.dist-info/WHEEL
pytest_change_assert-1.3.dist-info/entry_points.txt
pytest_change_assert-1.3.dist-info/top_level.txt
pytest_change_assert-1.3.dist-info/RECORD
